{
  "content": {
    "href": "https://api.spotify.com/v1/views/partner-recommendations?content_limit=5&locale=en_us&country=US&timestamp=2020-10-12T22:58:25.806822&types=track%2Calbum%2Cplaylist%2Cplaylist_v2%2Cartist%2Ccollection_artist%2Ccollection_album&signal=focus&limit=5&offset=0",
    "items": [
      {
        "content": {
          "href": "https://api.spotify.com/v1/views/partner-recently-played-v2?content_limit=5&locale=en_us&country=US&timestamp=2020-10-12T22:58:25.806822&types=track%2Calbum%2Cplaylist%2Cplaylist_v2%2Cartist%2Ccollection_artist%2Ccollection_album&signal=focus&limit=5&offset=0",
          "items": [
            {
              "collaborative": false,
              "description": "",
              "external_urls": {
                "spotify": "https://open.spotify.com/playlist/3xuQksXRTJEHIP79lbYqVy"
              },
              "href": "https://api.spotify.com/v1/playlists/3xuQksXRTJEHIP79lbYqVy",
              "id": "3xuQksXRTJEHIP79lbYqVy",
              "images": [
                {
                  "height": 640,
                  "url": "https://i.scdn.co/image/ab67616d00001e02c20c278a68424850767e4d9e",
                  "width": 640
                }
              ],
              "name": "Ori",
              "owner": {
                "display_name": "22ljto45czjwstx3coet7jd4a",
                "external_urls": {
                  "spotify": "https://open.spotify.com/user/22ljto45czjwstx3coet7jd4a"
                },
                "href": "https://api.spotify.com/v1/users/22ljto45czjwstx3coet7jd4a",
                "id": "22ljto45czjwstx3coet7jd4a",
                "type": "user",
                "uri": "spotify:user:22ljto45czjwstx3coet7jd4a"
              },
              "primary_color": null,
              "public": null,
              "snapshot_id": "MyxlNzhkOGI0M2Y2MTM2NzczZGU1MDRhM2FjZjgxZDBiM2FkNDY3NGQw",
              "tracks": {
                "href": "https://api.spotify.com/v1/playlists/3xuQksXRTJEHIP79lbYqVy/tracks",
                "total": 92
              },
              "type": "playlist",
              "uri": "spotify:playlist:3xuQksXRTJEHIP79lbYqVy"
            },
            {
              "collaborative": false,
              "description": "",
              "external_urls": {
                "spotify": "https://open.spotify.com/playlist/7LV3dDvULeO2PWeD17uV4m"
              },
              "href": "https://api.spotify.com/v1/playlists/7LV3dDvULeO2PWeD17uV4m",
              "id": "7LV3dDvULeO2PWeD17uV4m",
              "images": [
                {
                  "height": 640,
                  "url": "https://i.scdn.co/image/ab67616d00001e02c20c278a68424850767e4d9e",
                  "width": 640
                }
              ],
              "name": "Gareth Coker – Ori and the Will of the Wisps (Original Soundtrack Recording)",
              "owner": {
                "display_name": "22ljto45czjwstx3coet7jd4a",
                "external_urls": {
                  "spotify": "https://open.spotify.com/user/22ljto45czjwstx3coet7jd4a"
                },
                "href": "https://api.spotify.com/v1/users/22ljto45czjwstx3coet7jd4a",
                "id": "22ljto45czjwstx3coet7jd4a",
                "type": "user",
                "uri": "spotify:user:22ljto45czjwstx3coet7jd4a"
              },
              "primary_color": null,
              "public": null,
              "snapshot_id": "MixmYTBiOTI0YTBlYTBmNDVhZmQ3ZTFjNjJkZjE2NTkyNjJlM2JiZGYw",
              "tracks": {
                "href": "https://api.spotify.com/v1/playlists/7LV3dDvULeO2PWeD17uV4m/tracks",
                "total": 60
              },
              "type": "playlist",
              "uri": "spotify:playlist:7LV3dDvULeO2PWeD17uV4m"
            },
            {
              "collaborative": false,
              "description": "Drown in an ocean of atmospheric soundscapes.",
              "external_urls": {
                "spotify": "https://open.spotify.com/playlist/37i9dQZF1DX5y2yPmGqrG8"
              },
              "href": "https://api.spotify.com/v1/playlists/37i9dQZF1DX5y2yPmGqrG8",
              "id": "37i9dQZF1DX5y2yPmGqrG8",
              "images": [
                {
                  "height": null,
                  "url": "https://i.scdn.co/image/ab67706f000000026b70c40f47d72ad3fbe18322",
                  "width": null
                }
              ],
              "name": "Deep Listening",
              "owner": {
                "display_name": "Spotify",
                "external_urls": {
                  "spotify": "https://open.spotify.com/user/spotify"
                },
                "href": "https://api.spotify.com/v1/users/spotify",
                "id": "spotify",
                "type": "user",
                "uri": "spotify:user:spotify"
              },
              "primary_color": null,
              "public": null,
              "snapshot_id": "MTYwMjU0MzQ3NiwwMDAwMDAwMGQ0MWQ4Y2Q5OGYwMGIyMDRlOTgwMDk5OGVjZjg0Mjdl",
              "tracks": {
                "href": "https://api.spotify.com/v1/playlists/37i9dQZF1DX5y2yPmGqrG8/tracks",
                "total": 50
              },
              "type": "playlist",
              "uri": "spotify:playlist:37i9dQZF1DX5y2yPmGqrG8"
            },
            {
              "collaborative": false,
              "description": "",
              "external_urls": {
                "spotify": "https://open.spotify.com/playlist/78Lahg9leOxISL6tu3dhFV"
              },
              "href": "https://api.spotify.com/v1/playlists/78Lahg9leOxISL6tu3dhFV",
              "id": "78Lahg9leOxISL6tu3dhFV",
              "images": [
                {
                  "height": 640,
                  "url": "https://i.scdn.co/image/ab67616d00001e029251502f912751890b9f0321",
                  "width": 640
                }
              ],
              "name": "Hh",
              "owner": {
                "display_name": "22ljto45czjwstx3coet7jd4a",
                "external_urls": {
                  "spotify": "https://open.spotify.com/user/22ljto45czjwstx3coet7jd4a"
                },
                "href": "https://api.spotify.com/v1/users/22ljto45czjwstx3coet7jd4a",
                "id": "22ljto45czjwstx3coet7jd4a",
                "type": "user",
                "uri": "spotify:user:22ljto45czjwstx3coet7jd4a"
              },
              "primary_color": null,
              "public": null,
              "snapshot_id": "Myw5YTczY2Y3NmNhNWViOGQ3NGY0NjQ3ZDE5MDAyYjI3ZDdlYzhmMTZh",
              "tracks": {
                "href": "https://api.spotify.com/v1/playlists/78Lahg9leOxISL6tu3dhFV/tracks",
                "total": 1
              },
              "type": "playlist",
              "uri": "spotify:playlist:78Lahg9leOxISL6tu3dhFV"
            },
            {
              "collaborative": false,
              "description": "",
              "external_urls": {
                "spotify": "https://open.spotify.com/playlist/5Qj4LXNqPIKovGxnPjHF7Z"
              },
              "href": "https://api.spotify.com/v1/playlists/5Qj4LXNqPIKovGxnPjHF7Z",
              "id": "5Qj4LXNqPIKovGxnPjHF7Z",
              "images": [
                {
                  "height": 300,
                  "url": "https://i.scdn.co/image/ab67706c0000da84f3caef5ef78c679ffa50beed",
                  "width": 300
                }
              ],
              "name": "FreeCodeCamp Code Radio",
              "owner": {
                "display_name": "theradspaceman",
                "external_urls": {
                  "spotify": "https://open.spotify.com/user/theradspaceman"
                },
                "href": "https://api.spotify.com/v1/users/theradspaceman",
                "id": "theradspaceman",
                "type": "user",
                "uri": "spotify:user:theradspaceman"
              },
              "primary_color": null,
              "public": null,
              "snapshot_id": "OCw5YWRhN2YzNjJjNWI0ZTI1Njg5MTM3YmNkNmRhNmMwMGE2MWQ2MzA2",
              "tracks": {
                "href": "https://api.spotify.com/v1/playlists/5Qj4LXNqPIKovGxnPjHF7Z/tracks",
                "total": 87
              },
              "type": "playlist",
              "uri": "spotify:playlist:5Qj4LXNqPIKovGxnPjHF7Z"
            }
          ],
          "limit": 5,
          "next": "https://api.spotify.com/v1/views/partner-recently-played-v2?content_limit=5&locale=en_us&country=US&timestamp=2020-10-12T22:58:25.806822&types=track%2Calbum%2Cplaylist%2Cplaylist_v2%2Cartist%2Ccollection_artist%2Ccollection_album&signal=focus&limit=5&offset=5",
          "offset": 0,
          "previous": null,
          "total": 32
        },
        "custom_fields": {},
        "external_urls": null,
        "href": "https://api.spotify.com/v1/views/partner-recently-played-v2",
        "id": "partner-recently-played-v2",
        "images": [],
        "name": "Recently played",
        "rendering": "CAROUSEL",
        "tag_line": null,
        "type": "view"
      },
      {
        "content": {
          "href": "https://api.spotify.com/v1/views/partner-home-made-for-x?content_limit=5&locale=en_us&country=US&timestamp=2020-10-12T22:58:25.806822&types=track%2Calbum%2Cplaylist%2Cplaylist_v2%2Cartist%2Ccollection_artist%2Ccollection_album&signal=focus&limit=5&offset=0",
          "items": [
            {
              "collaborative": false,
              "description": "Your weekly mixtape of fresh music. Enjoy new music and deep cuts picked for you. Updates every Monday.",
              "external_urls": {
                "spotify": "https://open.spotify.com/playlist/37i9dQZEVXcKhFwbIaVuE2"
              },
              "href": "https://api.spotify.com/v1/playlists/37i9dQZEVXcKhFwbIaVuE2",
              "id": "37i9dQZEVXcKhFwbIaVuE2",
              "images": [
                {
                  "height": null,
                  "url": "https://newjams-images.scdn.co/v2/discover-weekly/aAbca4VNfzWuUCQ_FGiEFA==/bmVuZW5lbmVuZW5lbmVuZQ==/default",
                  "width": null
                }
              ],
              "name": "Discover Weekly",
              "owner": {
                "display_name": "Spotify",
                "external_urls": {
                  "spotify": "https://open.spotify.com/user/spotify"
                },
                "href": "https://api.spotify.com/v1/users/spotify",
                "id": "spotify",
                "type": "user",
                "uri": "spotify:user:spotify"
              },
              "primary_color": null,
              "public": null,
              "snapshot_id": "MjY3MDc2ODAsMDAwMDAwMDBmNWE0N2M2NzZlNjc3Yzg0NTQzMmYyY2ViNzdmYTJkOQ==",
              "tracks": {
                "href": "https://api.spotify.com/v1/playlists/37i9dQZEVXcKhFwbIaVuE2/tracks",
                "total": 30
              },
              "type": "playlist",
              "uri": "spotify:playlist:37i9dQZEVXcKhFwbIaVuE2"
            },
            {
              "collaborative": false,
              "description": "Vampire Weekend, EASYFUN, Arca and more",
              "external_urls": {
                "spotify": "https://open.spotify.com/playlist/37i9dQZF1E37BRj7vruNlq"
              },
              "href": "https://api.spotify.com/v1/playlists/37i9dQZF1E37BRj7vruNlq",
              "id": "37i9dQZF1E37BRj7vruNlq",
              "images": [
                {
                  "height": null,
                  "url": "https://dailymix-images.scdn.co/v2/img/5390ca6bd240b2a15b71868d1d105c3d6a7a7b17/1/en/default",
                  "width": null
                }
              ],
              "name": "Daily Mix 1",
              "owner": {
                "display_name": "Spotify",
                "external_urls": {
                  "spotify": "https://open.spotify.com/user/spotify"
                },
                "href": "https://api.spotify.com/v1/users/spotify",
                "id": "spotify",
                "type": "user",
                "uri": "spotify:user:spotify"
              },
              "primary_color": null,
              "public": null,
              "snapshot_id": "MjY3MDkwNTgsMDAwMDAwMDBmNTM2MDdmZDVlNWFiYjRjZTY2YmY4ZmJkMGEyMDc4Yg==",
              "tracks": {
                "href": "https://api.spotify.com/v1/playlists/37i9dQZF1E37BRj7vruNlq/tracks",
                "total": 50
              },
              "type": "playlist",
              "uri": "spotify:playlist:37i9dQZF1E37BRj7vruNlq"
            },
            {
              "collaborative": false,
              "description": "FJAAK, Trudge, DLV and more",
              "external_urls": {
                "spotify": "https://open.spotify.com/playlist/37i9dQZF1E36d1ADnE7fxm"
              },
              "href": "https://api.spotify.com/v1/playlists/37i9dQZF1E36d1ADnE7fxm",
              "id": "37i9dQZF1E36d1ADnE7fxm",
              "images": [
                {
                  "height": null,
                  "url": "https://dailymix-images.scdn.co/v2/img/70fe11f610c2936851c846ed5bd5ffe9f3831993/2/en/default",
                  "width": null
                }
              ],
              "name": "Daily Mix 2",
              "owner": {
                "display_name": "Spotify",
                "external_urls": {
                  "spotify": "https://open.spotify.com/user/spotify"
                },
                "href": "https://api.spotify.com/v1/users/spotify",
                "id": "spotify",
                "type": "user",
                "uri": "spotify:user:spotify"
              },
              "primary_color": null,
              "public": null,
              "snapshot_id": "MjY3MDkwNTgsMDAwMDAwMDBhNGExNmM5Nzc5YmM0ZTE3ZWJkNTAzMTNlNWY4YWUwNg==",
              "tracks": {
                "href": "https://api.spotify.com/v1/playlists/37i9dQZF1E36d1ADnE7fxm/tracks",
                "total": 50
              },
              "type": "playlist",
              "uri": "spotify:playlist:37i9dQZF1E36d1ADnE7fxm"
            },
            {
              "collaborative": false,
              "description": "The Beatles, John Denver, The Rolling Stones and more",
              "external_urls": {
                "spotify": "https://open.spotify.com/playlist/37i9dQZF1E35jQVwJqYXaU"
              },
              "href": "https://api.spotify.com/v1/playlists/37i9dQZF1E35jQVwJqYXaU",
              "id": "37i9dQZF1E35jQVwJqYXaU",
              "images": [
                {
                  "height": null,
                  "url": "https://dailymix-images.scdn.co/v2/img/6b2a709752ef9c7aaf0d270344157f6cd2e0f1a7/3/en/default",
                  "width": null
                }
              ],
              "name": "Daily Mix 3",
              "owner": {
                "display_name": "Spotify",
                "external_urls": {
                  "spotify": "https://open.spotify.com/user/spotify"
                },
                "href": "https://api.spotify.com/v1/users/spotify",
                "id": "spotify",
                "type": "user",
                "uri": "spotify:user:spotify"
              },
              "primary_color": null,
              "public": null,
              "snapshot_id": "MjY3MDkwNTgsMDAwMDAwMDAwZTFmMTNlMGFhODk1YTQwMTE3NmZhYThkNjU2MTQwYQ==",
              "tracks": {
                "href": "https://api.spotify.com/v1/playlists/37i9dQZF1E35jQVwJqYXaU/tracks",
                "total": 50
              },
              "type": "playlist",
              "uri": "spotify:playlist:37i9dQZF1E35jQVwJqYXaU"
            },
            {
              "collaborative": false,
              "description": "Andreas Scholl, Fazil Say, Yo-Yo Ma and more",
              "external_urls": {
                "spotify": "https://open.spotify.com/playlist/37i9dQZF1E37iB2PxN3dCg"
              },
              "href": "https://api.spotify.com/v1/playlists/37i9dQZF1E37iB2PxN3dCg",
              "id": "37i9dQZF1E37iB2PxN3dCg",
              "images": [
                {
                  "height": null,
                  "url": "https://dailymix-images.scdn.co/v2/img/44dd0f1287dc49982257cd4eacb13f02f36e5a5c/4/en/default",
                  "width": null
                }
              ],
              "name": "Daily Mix 4",
              "owner": {
                "display_name": "Spotify",
                "external_urls": {
                  "spotify": "https://open.spotify.com/user/spotify"
                },
                "href": "https://api.spotify.com/v1/users/spotify",
                "id": "spotify",
                "type": "user",
                "uri": "spotify:user:spotify"
              },
              "primary_color": null,
              "public": null,
              "snapshot_id": "MjY3MDkwNTgsMDAwMDAwMDA1MGVhNWU4YmEwZGJmNzFhYjRiOTA3NDQ5YTNlNjBhMA==",
              "tracks": {
                "href": "https://api.spotify.com/v1/playlists/37i9dQZF1E37iB2PxN3dCg/tracks",
                "total": 50
              },
              "type": "playlist",
              "uri": "spotify:playlist:37i9dQZF1E37iB2PxN3dCg"
            }
          ],
          "limit": 5,
          "next": "https://api.spotify.com/v1/views/partner-home-made-for-x?content_limit=5&locale=en_us&country=US&timestamp=2020-10-12T22:58:25.806822&types=track%2Calbum%2Cplaylist%2Cplaylist_v2%2Cartist%2Ccollection_artist%2Ccollection_album&signal=focus&limit=5&offset=5",
          "offset": 0,
          "previous": null,
          "total": 12
        },
        "custom_fields": {},
        "external_urls": null,
        "href": "https://api.spotify.com/v1/views/partner-home-made-for-x",
        "id": "partner-home-made-for-x",
        "images": [],
        "name": "Made for you",
        "rendering": "CAROUSEL",
        "tag_line": "Get better recommendations the more you listen.",
        "type": "view"
      },
      {
        "content": {
          "href": "https://api.spotify.com/v1/views/dense-ginger-featured-playlists?content_limit=5&locale=en_us&country=US&timestamp=2020-10-12T22:58:25.806822&types=track%2Calbum%2Cplaylist%2Cplaylist_v2%2Cartist%2Ccollection_artist%2Ccollection_album&signal=focus&limit=5&offset=0",
          "items": [
            {
              "collaborative": false,
              "description": "The chillest instrumental lofi beats, certified lush.",
              "external_urls": {
                "spotify": "https://open.spotify.com/playlist/37i9dQZF1DXc8kgYqQLMfH"
              },
              "href": "https://api.spotify.com/v1/playlists/37i9dQZF1DXc8kgYqQLMfH",
              "id": "37i9dQZF1DXc8kgYqQLMfH",
              "images": [
                {
                  "height": null,
                  "url": "https://i.scdn.co/image/ab67706f00000002a26911885a1acf38f16c5d51",
                  "width": null
                }
              ],
              "name": "Lush Lofi",
              "owner": {
                "display_name": "Spotify",
                "external_urls": {
                  "spotify": "https://open.spotify.com/user/spotify"
                },
                "href": "https://api.spotify.com/v1/users/spotify",
                "id": "spotify",
                "type": "user",
                "uri": "spotify:user:spotify"
              },
              "primary_color": null,
              "public": null,
              "snapshot_id": "MTU5ODY1NTk2NiwwMDAwMDA5MjAwMDAwMTc0Mzc1MjJlYzQwMDAwMDE2ZDE1M2M2ZmNl",
              "tracks": {
                "href": "https://api.spotify.com/v1/playlists/37i9dQZF1DXc8kgYqQLMfH/tracks",
                "total": 114
              },
              "type": "playlist",
              "uri": "spotify:playlist:37i9dQZF1DXc8kgYqQLMfH"
            },
            {
              "collaborative": false,
              "description": "Stay focused with electronic and trap beats.",
              "external_urls": {
                "spotify": "https://open.spotify.com/playlist/37i9dQZF1DX692WcMwL2yW"
              },
              "href": "https://api.spotify.com/v1/playlists/37i9dQZF1DX692WcMwL2yW",
              "id": "37i9dQZF1DX692WcMwL2yW",
              "images": [
                {
                  "height": null,
                  "url": "https://i.scdn.co/image/ab67706f0000000258db4ac7cd52e1a5b2c9d84b",
                  "width": null
                }
              ],
              "name": "All-Nighter",
              "owner": {
                "display_name": "Spotify",
                "external_urls": {
                  "spotify": "https://open.spotify.com/user/spotify"
                },
                "href": "https://api.spotify.com/v1/users/spotify",
                "id": "spotify",
                "type": "user",
                "uri": "spotify:user:spotify"
              },
              "primary_color": null,
              "public": null,
              "snapshot_id": "MTU5OTE4Nzg0NiwwMDAwMDAwZTAwMDAwMTc0NTcwNjA2NGUwMDAwMDE3MGFmNDBhM2M0",
              "tracks": {
                "href": "https://api.spotify.com/v1/playlists/37i9dQZF1DX692WcMwL2yW/tracks",
                "total": 83
              },
              "type": "playlist",
              "uri": "spotify:playlist:37i9dQZF1DX692WcMwL2yW"
            },
            {
              "collaborative": false,
              "description": "The tracks that gamers love.",
              "external_urls": {
                "spotify": "https://open.spotify.com/playlist/37i9dQZF1DWTyiBJ6yEqeu"
              },
              "href": "https://api.spotify.com/v1/playlists/37i9dQZF1DWTyiBJ6yEqeu",
              "id": "37i9dQZF1DWTyiBJ6yEqeu",
              "images": [
                {
                  "height": null,
                  "url": "https://i.scdn.co/image/ab67706f0000000293e494dfa690515c1dad5885",
                  "width": null
                }
              ],
              "name": "Top Gaming Tracks",
              "owner": {
                "display_name": "Spotify",
                "external_urls": {
                  "spotify": "https://open.spotify.com/user/spotify"
                },
                "href": "https://api.spotify.com/v1/users/spotify",
                "id": "spotify",
                "type": "user",
                "uri": "spotify:user:spotify"
              },
              "primary_color": null,
              "public": null,
              "snapshot_id": "MTYwMjU0MzQ4MCwwMDAwMDAwMGQ0MWQ4Y2Q5OGYwMGIyMDRlOTgwMDk5OGVjZjg0Mjdl",
              "tracks": {
                "href": "https://api.spotify.com/v1/playlists/37i9dQZF1DWTyiBJ6yEqeu/tracks",
                "total": 50
              },
              "type": "playlist",
              "uri": "spotify:playlist:37i9dQZF1DWTyiBJ6yEqeu"
            },
            {
              "collaborative": false,
              "description": "songs u can send to ur friends, or keep for urself :') ft Wallows",
              "external_urls": {
                "spotify": "https://open.spotify.com/playlist/37i9dQZF1DXdwmD5Q7Gxah"
              },
              "href": "https://api.spotify.com/v1/playlists/37i9dQZF1DXdwmD5Q7Gxah",
              "id": "37i9dQZF1DXdwmD5Q7Gxah",
              "images": [
                {
                  "height": null,
                  "url": "https://i.scdn.co/image/ab67706f00000002002a31069320bf5ae112675f",
                  "width": null
                }
              ],
              "name": "Lorem",
              "owner": {
                "display_name": "Spotify",
                "external_urls": {
                  "spotify": "https://open.spotify.com/user/spotify"
                },
                "href": "https://api.spotify.com/v1/users/spotify",
                "id": "spotify",
                "type": "user",
                "uri": "spotify:user:spotify"
              },
              "primary_color": null,
              "public": null,
              "snapshot_id": "MTYwMjI4MTY3OCwwMDAwMDFmNTAwMDAwMTc1MGY2ZTI4NGMwMDAwMDE3NGZhZjViODc4",
              "tracks": {
                "href": "https://api.spotify.com/v1/playlists/37i9dQZF1DXdwmD5Q7Gxah/tracks",
                "total": 150
              },
              "type": "playlist",
              "uri": "spotify:playlist:37i9dQZF1DXdwmD5Q7Gxah"
            },
            {
              "collaborative": false,
              "description": "Hypnotic bliss.",
              "external_urls": {
                "spotify": "https://open.spotify.com/playlist/37i9dQZF1DWSiZVO2J6WeI"
              },
              "href": "https://api.spotify.com/v1/playlists/37i9dQZF1DWSiZVO2J6WeI",
              "id": "37i9dQZF1DWSiZVO2J6WeI",
              "images": [
                {
                  "height": null,
                  "url": "https://i.scdn.co/image/ab67706f00000002cef1e1e83454017583e8bd8f",
                  "width": null
                }
              ],
              "name": "Dreamy Vibes",
              "owner": {
                "display_name": "Spotify",
                "external_urls": {
                  "spotify": "https://open.spotify.com/user/spotify"
                },
                "href": "https://api.spotify.com/v1/users/spotify",
                "id": "spotify",
                "type": "user",
                "uri": "spotify:user:spotify"
              },
              "primary_color": null,
              "public": null,
              "snapshot_id": "MTYwMjU0MzQ1MywwMDAwMDAwMGQ0MWQ4Y2Q5OGYwMGIyMDRlOTgwMDk5OGVjZjg0Mjdl",
              "tracks": {
                "href": "https://api.spotify.com/v1/playlists/37i9dQZF1DWSiZVO2J6WeI/tracks",
                "total": 100
              },
              "type": "playlist",
              "uri": "spotify:playlist:37i9dQZF1DWSiZVO2J6WeI"
            }
          ],
          "limit": 5,
          "next": "https://api.spotify.com/v1/views/dense-ginger-featured-playlists?content_limit=5&locale=en_us&country=US&timestamp=2020-10-12T22:58:25.806822&types=track%2Calbum%2Cplaylist%2Cplaylist_v2%2Cartist%2Ccollection_artist%2Ccollection_album&signal=focus&limit=5&offset=5",
          "offset": 0,
          "previous": null,
          "total": 10
        },
        "custom_fields": {},
        "external_urls": null,
        "href": "https://api.spotify.com/v1/views/dense-ginger-featured-playlists",
        "id": "dense-ginger-featured-playlists",
        "images": [],
        "name": "Wind down",
        "rendering": "CAROUSEL",
        "tag_line": null,
        "type": "view"
      },
      {
        "content": {
          "href": "https://api.spotify.com/v1/views/ginger-genre-affinity%5B0%5D?content_limit=5&locale=en_us&country=US&timestamp=2020-10-12T22:58:25.806822&types=track%2Calbum%2Cplaylist%2Cplaylist_v2%2Cartist%2Ccollection_artist%2Ccollection_album&signal=focus&limit=5&offset=0",
          "items": [
            {
              "collaborative": false,
              "description": "The world's biggest dance hits. New Music from Jax Jones & Au/Ra, Tchami and Channel Tres.",
              "external_urls": {
                "spotify": "https://open.spotify.com/playlist/37i9dQZF1DX4dyzvuaRJ0n"
              },
              "href": "https://api.spotify.com/v1/playlists/37i9dQZF1DX4dyzvuaRJ0n",
              "id": "37i9dQZF1DX4dyzvuaRJ0n",
              "images": [
                {
                  "height": null,
                  "url": "https://i.scdn.co/image/ab67706f000000027dbf92be005a887d3499ec1f",
                  "width": null
                }
              ],
              "name": "mint",
              "owner": {
                "display_name": "Spotify",
                "external_urls": {
                  "spotify": "https://open.spotify.com/user/spotify"
                },
                "href": "https://api.spotify.com/v1/users/spotify",
                "id": "spotify",
                "type": "user",
                "uri": "spotify:user:spotify"
              },
              "primary_color": null,
              "public": null,
              "snapshot_id": "MTYwMjIxOTY2MCwwMDAwMDQ2MjAwMDAwMTc1MGJiYmQzOTcwMDAwMDE3NTA5NTkxZjBm",
              "tracks": {
                "href": "https://api.spotify.com/v1/playlists/37i9dQZF1DX4dyzvuaRJ0n/tracks",
                "total": 73
              },
              "type": "playlist",
              "uri": "spotify:playlist:37i9dQZF1DX4dyzvuaRJ0n"
            },
            {
              "collaborative": false,
              "description": "All the <a href=\"spotify:genre:edm_dance\">big ones</a> with SAINt JHN",
              "external_urls": {
                "spotify": "https://open.spotify.com/playlist/37i9dQZF1DX0BcQWzuB7ZO"
              },
              "href": "https://api.spotify.com/v1/playlists/37i9dQZF1DX0BcQWzuB7ZO",
              "id": "37i9dQZF1DX0BcQWzuB7ZO",
              "images": [
                {
                  "height": null,
                  "url": "https://i.scdn.co/image/ab67706f00000002523895ded8cbebd430d90acb",
                  "width": null
                }
              ],
              "name": "Dance Hits",
              "owner": {
                "display_name": "Spotify",
                "external_urls": {
                  "spotify": "https://open.spotify.com/user/spotify"
                },
                "href": "https://api.spotify.com/v1/users/spotify",
                "id": "spotify",
                "type": "user",
                "uri": "spotify:user:spotify"
              },
              "primary_color": null,
              "public": null,
              "snapshot_id": "MTYwMjU0MzQ1NCwwMDAwMDAwMGQ0MWQ4Y2Q5OGYwMGIyMDRlOTgwMDk5OGVjZjg0Mjdl",
              "tracks": {
                "href": "https://api.spotify.com/v1/playlists/37i9dQZF1DX0BcQWzuB7ZO/tracks",
                "total": 100
              },
              "type": "playlist",
              "uri": "spotify:playlist:37i9dQZF1DX0BcQWzuB7ZO"
            },
            {
              "collaborative": false,
              "description": "Aggressive trap and bass for the <a href=\"spotify:genre:edm_dance\">gym</a>.",
              "external_urls": {
                "spotify": "https://open.spotify.com/playlist/37i9dQZF1DX4eRPd9frC1m"
              },
              "href": "https://api.spotify.com/v1/playlists/37i9dQZF1DX4eRPd9frC1m",
              "id": "37i9dQZF1DX4eRPd9frC1m",
              "images": [
                {
                  "height": null,
                  "url": "https://i.scdn.co/image/ab67706f00000002122921a072ad2ca9ce90a456",
                  "width": null
                }
              ],
              "name": "Hype",
              "owner": {
                "display_name": "Spotify",
                "external_urls": {
                  "spotify": "https://open.spotify.com/user/spotify"
                },
                "href": "https://api.spotify.com/v1/users/spotify",
                "id": "spotify",
                "type": "user",
                "uri": "spotify:user:spotify"
              },
              "primary_color": null,
              "public": null,
              "snapshot_id": "MTYwMjU0MzQ3NywwMDAwMDAwMGQ0MWQ4Y2Q5OGYwMGIyMDRlOTgwMDk5OGVjZjg0Mjdl",
              "tracks": {
                "href": "https://api.spotify.com/v1/playlists/37i9dQZF1DX4eRPd9frC1m/tracks",
                "total": 179
              },
              "type": "playlist",
              "uri": "spotify:playlist:37i9dQZF1DX4eRPd9frC1m"
            },
            {
              "collaborative": false,
              "description": "Mixing midtempo <a href=\"spotify:genre:bass\">bass</a>, dub, trap and more low-end frequency with WHIPPED CREAM",
              "external_urls": {
                "spotify": "https://open.spotify.com/playlist/37i9dQZF1DX0hvSv9Rf41p"
              },
              "href": "https://api.spotify.com/v1/playlists/37i9dQZF1DX0hvSv9Rf41p",
              "id": "37i9dQZF1DX0hvSv9Rf41p",
              "images": [
                {
                  "height": null,
                  "url": "https://i.scdn.co/image/ab67706f000000027872f2f35b448e609c2d3efd",
                  "width": null
                }
              ],
              "name": "Bass Arcade",
              "owner": {
                "display_name": "Spotify",
                "external_urls": {
                  "spotify": "https://open.spotify.com/user/spotify"
                },
                "href": "https://api.spotify.com/v1/users/spotify",
                "id": "spotify",
                "type": "user",
                "uri": "spotify:user:spotify"
              },
              "primary_color": null,
              "public": null,
              "snapshot_id": "MTYwMjU0MzQ1NCwwMDAwMDAwMGQ0MWQ4Y2Q5OGYwMGIyMDRlOTgwMDk5OGVjZjg0Mjdl",
              "tracks": {
                "href": "https://api.spotify.com/v1/playlists/37i9dQZF1DX0hvSv9Rf41p/tracks",
                "total": 90
              },
              "type": "playlist",
              "uri": "spotify:playlist:37i9dQZF1DX0hvSv9Rf41p"
            },
            {
              "collaborative": false,
              "description": "Feel-good <a href=\"spotify:genre:edm_dance\">dance music</a>!",
              "external_urls": {
                "spotify": "https://open.spotify.com/playlist/37i9dQZF1DWSf2RDTDayIx"
              },
              "href": "https://api.spotify.com/v1/playlists/37i9dQZF1DWSf2RDTDayIx",
              "id": "37i9dQZF1DWSf2RDTDayIx",
              "images": [
                {
                  "height": null,
                  "url": "https://i.scdn.co/image/ab67706f00000002fe0099a8dcd3054706ffc92f",
                  "width": null
                }
              ],
              "name": "Happy Beats",
              "owner": {
                "display_name": "Spotify",
                "external_urls": {
                  "spotify": "https://open.spotify.com/user/spotify"
                },
                "href": "https://api.spotify.com/v1/users/spotify",
                "id": "spotify",
                "type": "user",
                "uri": "spotify:user:spotify"
              },
              "primary_color": null,
              "public": null,
              "snapshot_id": "MTYwMjU0MzQ3OCwwMDAwMDAwMGQ0MWQ4Y2Q5OGYwMGIyMDRlOTgwMDk5OGVjZjg0Mjdl",
              "tracks": {
                "href": "https://api.spotify.com/v1/playlists/37i9dQZF1DWSf2RDTDayIx/tracks",
                "total": 101
              },
              "type": "playlist",
              "uri": "spotify:playlist:37i9dQZF1DWSf2RDTDayIx"
            }
          ],
          "limit": 5,
          "next": "https://api.spotify.com/v1/views/ginger-genre-affinity%5B0%5D?content_limit=5&locale=en_us&country=US&timestamp=2020-10-12T22:58:25.806822&types=track%2Calbum%2Cplaylist%2Cplaylist_v2%2Cartist%2Ccollection_artist%2Ccollection_album&signal=focus&limit=5&offset=5",
          "offset": 0,
          "previous": null,
          "total": 11
        },
        "custom_fields": {},
        "external_urls": null,
        "href": "https://api.spotify.com/v1/views/ginger-genre-affinity%5B0%5D",
        "id": "ginger-genre-affinity[0]",
        "images": [],
        "name": "Electronic/Dance",
        "rendering": "CAROUSEL",
        "tag_line": "Recommended for you.",
        "type": "view"
      },
      {
        "content": {
          "href": "https://api.spotify.com/v1/views/ginger-genre-affinity%5B1%5D?content_limit=5&locale=en_us&country=US&timestamp=2020-10-12T22:58:25.806822&types=track%2Calbum%2Cplaylist%2Cplaylist_v2%2Cartist%2Ccollection_artist%2Ccollection_album&signal=focus&limit=5&offset=0",
          "items": [
            {
              "collaborative": false,
              "description": "every main character needs their soundtrack",
              "external_urls": {
                "spotify": "https://open.spotify.com/playlist/37i9dQZF1DX4OzrY981I1W"
              },
              "href": "https://api.spotify.com/v1/playlists/37i9dQZF1DX4OzrY981I1W",
              "id": "37i9dQZF1DX4OzrY981I1W",
              "images": [
                {
                  "height": null,
                  "url": "https://i.scdn.co/image/ab67706f00000002d2789b816dfcdc308c56fb33",
                  "width": null
                }
              ],
              "name": "my life is a movie",
              "owner": {
                "display_name": "Spotify",
                "external_urls": {
                  "spotify": "https://open.spotify.com/user/spotify"
                },
                "href": "https://api.spotify.com/v1/users/spotify",
                "id": "spotify",
                "type": "user",
                "uri": "spotify:user:spotify"
              },
              "primary_color": null,
              "public": null,
              "snapshot_id": "MTYwMjU0MzQ3OSwwMDAwMDAwMGQ0MWQ4Y2Q5OGYwMGIyMDRlOTgwMDk5OGVjZjg0Mjdl",
              "tracks": {
                "href": "https://api.spotify.com/v1/playlists/37i9dQZF1DX4OzrY981I1W/tracks",
                "total": 75
              },
              "type": "playlist",
              "uri": "spotify:playlist:37i9dQZF1DX4OzrY981I1W"
            },
            {
              "collaborative": false,
              "description": "Genre-less. Quality first always. Cover: Simpson",
              "external_urls": {
                "spotify": "https://open.spotify.com/playlist/37i9dQZF1DWWBHeXOYZf74"
              },
              "href": "https://api.spotify.com/v1/playlists/37i9dQZF1DWWBHeXOYZf74",
              "id": "37i9dQZF1DWWBHeXOYZf74",
              "images": [
                {
                  "height": null,
                  "url": "https://i.scdn.co/image/ab67706f00000002458b11f62ac0b4098f2ee3e3",
                  "width": null
                }
              ],
              "name": "POLLEN",
              "owner": {
                "display_name": "Spotify",
                "external_urls": {
                  "spotify": "https://open.spotify.com/user/spotify"
                },
                "href": "https://api.spotify.com/v1/users/spotify",
                "id": "spotify",
                "type": "user",
                "uri": "spotify:user:spotify"
              },
              "primary_color": null,
              "public": null,
              "snapshot_id": "MTYwMjIxNjA2MCwwMDAwMDJkYzAwMDAwMTc1MGI4NGU1YTQwMDAwMDE3NTBiNTYwZTM5",
              "tracks": {
                "href": "https://api.spotify.com/v1/playlists/37i9dQZF1DWWBHeXOYZf74/tracks",
                "total": 169
              },
              "type": "playlist",
              "uri": "spotify:playlist:37i9dQZF1DWWBHeXOYZf74"
            },
            {
              "collaborative": false,
              "description": "We hear you",
              "external_urls": {
                "spotify": "https://open.spotify.com/playlist/37i9dQZF1DX59NCqCqJtoH"
              },
              "href": "https://api.spotify.com/v1/playlists/37i9dQZF1DX59NCqCqJtoH",
              "id": "37i9dQZF1DX59NCqCqJtoH",
              "images": [
                {
                  "height": null,
                  "url": "https://i.scdn.co/image/ab67706f000000025f6755807c73eb5f0effb5f0",
                  "width": null
                }
              ],
              "name": "idk.",
              "owner": {
                "display_name": "Spotify",
                "external_urls": {
                  "spotify": "https://open.spotify.com/user/spotify"
                },
                "href": "https://api.spotify.com/v1/users/spotify",
                "id": "spotify",
                "type": "user",
                "uri": "spotify:user:spotify"
              },
              "primary_color": null,
              "public": null,
              "snapshot_id": "MTYwMjU0MzQ3OSwwMDAwMDAwMGQ0MWQ4Y2Q5OGYwMGIyMDRlOTgwMDk5OGVjZjg0Mjdl",
              "tracks": {
                "href": "https://api.spotify.com/v1/playlists/37i9dQZF1DX59NCqCqJtoH/tracks",
                "total": 100
              },
              "type": "playlist",
              "uri": "spotify:playlist:37i9dQZF1DX59NCqCqJtoH"
            },
            {
              "collaborative": false,
              "description": "New and approved indie pop. Cover: mxmtoon",
              "external_urls": {
                "spotify": "https://open.spotify.com/playlist/37i9dQZF1DWWEcRhUVtL8n"
              },
              "href": "https://api.spotify.com/v1/playlists/37i9dQZF1DWWEcRhUVtL8n",
              "id": "37i9dQZF1DWWEcRhUVtL8n",
              "images": [
                {
                  "height": null,
                  "url": "https://i.scdn.co/image/ab67706f0000000287253a291ce818e26803b152",
                  "width": null
                }
              ],
              "name": "Indie Pop",
              "owner": {
                "display_name": "Spotify",
                "external_urls": {
                  "spotify": "https://open.spotify.com/user/spotify"
                },
                "href": "https://api.spotify.com/v1/users/spotify",
                "id": "spotify",
                "type": "user",
                "uri": "spotify:user:spotify"
              },
              "primary_color": null,
              "public": null,
              "snapshot_id": "MTYwMjU0MzQ3NywwMDAwMDAwMGQ0MWQ4Y2Q5OGYwMGIyMDRlOTgwMDk5OGVjZjg0Mjdl",
              "tracks": {
                "href": "https://api.spotify.com/v1/playlists/37i9dQZF1DWWEcRhUVtL8n/tracks",
                "total": 100
              },
              "type": "playlist",
              "uri": "spotify:playlist:37i9dQZF1DWWEcRhUVtL8n"
            },
            {
              "collaborative": false,
              "description": "The best new tracks every week. Cover: Future Islands",
              "external_urls": {
                "spotify": "https://open.spotify.com/playlist/37i9dQZF1DXdbXrPNafg9d"
              },
              "href": "https://api.spotify.com/v1/playlists/37i9dQZF1DXdbXrPNafg9d",
              "id": "37i9dQZF1DXdbXrPNafg9d",
              "images": [
                {
                  "height": null,
                  "url": "https://i.scdn.co/image/ab67706f00000002d8c0189735d0fc2ab4bb85cf",
                  "width": null
                }
              ],
              "name": "All New Indie",
              "owner": {
                "display_name": "Spotify",
                "external_urls": {
                  "spotify": "https://open.spotify.com/user/spotify"
                },
                "href": "https://api.spotify.com/v1/users/spotify",
                "id": "spotify",
                "type": "user",
                "uri": "spotify:user:spotify"
              },
              "primary_color": null,
              "public": null,
              "snapshot_id": "MTYwMjIxNjA2MCwwMDAwMDIwMDAwMDAwMTc1MGI4NGU2MmMwMDAwMDE3NTBhMzExYzc4",
              "tracks": {
                "href": "https://api.spotify.com/v1/playlists/37i9dQZF1DXdbXrPNafg9d/tracks",
                "total": 132
              },
              "type": "playlist",
              "uri": "spotify:playlist:37i9dQZF1DXdbXrPNafg9d"
            }
          ],
          "limit": 5,
          "next": "https://api.spotify.com/v1/views/ginger-genre-affinity%5B1%5D?content_limit=5&locale=en_us&country=US&timestamp=2020-10-12T22:58:25.806822&types=track%2Calbum%2Cplaylist%2Cplaylist_v2%2Cartist%2Ccollection_artist%2Ccollection_album&signal=focus&limit=5&offset=5",
          "offset": 0,
          "previous": null,
          "total": 10
        },
        "custom_fields": {},
        "external_urls": null,
        "href": "https://api.spotify.com/v1/views/ginger-genre-affinity%5B1%5D",
        "id": "ginger-genre-affinity[1]",
        "images": [],
        "name": "Indie",
        "rendering": "CAROUSEL",
        "tag_line": "Recommended for you.",
        "type": "view"
      }
    ],
    "limit": 5,
    "next": "https://api.spotify.com/v1/views/partner-recommendations?content_limit=5&locale=en_us&country=US&timestamp=2020-10-12T22:58:25.806822&types=track%2Calbum%2Cplaylist%2Cplaylist_v2%2Cartist%2Ccollection_artist%2Ccollection_album&signal=focus&limit=5&offset=5",
    "offset": 0,
    "previous": null,
    "total": 20
  },
  "custom_fields": {},
  "external_urls": null,
  "href": "https://api.spotify.com/v1/views/partner-recommendations",
  "id": "partner-recommendations",
  "images": [],
  "name": null,
  "rendering": "STACK",
  "tag_line": null,
  "type": "view"
}